kafka_messaging/__init__.py
kafka_messaging/listener.py
kafka_messaging/listener_pool.py
kafka_messaging/sender.py
kafka_messaging-1.1.1.dist-info/LICENSE
kafka_messaging-1.1.1.dist-info/METADATA
kafka_messaging-1.1.1.dist-info/WHEEL
kafka_messaging-1.1.1.dist-info/top_level.txt
kafka_messaging-1.1.1.dist-info/RECORD
