Metadata-Version: 2.1
Name: kafka-messaging
Version: 1.1.1
Summary: Simple interface for sending messages through Kafka
Home-page: https://gitlab.com/zaitt_computer_vision/kafka_api
Author: Andre Ferrari Moukarzel
Author-email: andremoukarzel@gmail.com
License: MIT
Platform: UNKNOWN
Requires-Python: >=3.6
Requires-Dist: confluent-kafka
